hc_go_plugin_server/__init__.py
hc_go_plugin_server/_async/__init__.py
hc_go_plugin_server/_async/controller_servicer.py
hc_go_plugin_server/_async/rpc_plugin_server.py
hc_go_plugin_server/_common/__init__.py
hc_go_plugin_server/_common/rpc_plugin_server.py
hc_go_plugin_server/_sync/__init__.py
hc_go_plugin_server/_sync/controller_servicer.py
hc_go_plugin_server/_sync/rpc_plugin_server.py
hc_go_plugin_server/controller_servicer.py
hc_go_plugin_server/daemon_task.py
hc_go_plugin_server/grpc_controller_pb2.py
hc_go_plugin_server/grpc_controller_pb2.pyi
hc_go_plugin_server/grpc_controller_pb2_grpc.py
hc_go_plugin_server/grpc_server.py
hc_go_plugin_server/grpc_server_factory.py
hc_go_plugin_server/health_servicer.py
hc_go_plugin_server/py.typed
hc_go_plugin_server/rpc_plugin.py
hc_go_plugin_server-0.1.1.dist-info/LICENSE
hc_go_plugin_server-0.1.1.dist-info/METADATA
hc_go_plugin_server-0.1.1.dist-info/WHEEL
hc_go_plugin_server-0.1.1.dist-info/RECORD
